alphaconfig/AlphaConfig.py
alphaconfig/__init__.py
alphaconfig-0.0.3.dist-info/LICENSE
alphaconfig-0.0.3.dist-info/METADATA
alphaconfig-0.0.3.dist-info/WHEEL
alphaconfig-0.0.3.dist-info/top_level.txt
alphaconfig-0.0.3.dist-info/RECORD
