Metadata-Version: 2.1
Name: alphaconfig
Version: 0.0.3
Summary: An easy module for configuration
Home-page: https://github.com/yiqunchen1999/alphaconfig
Author: Yiqun Chen
Author-email: yiqunchen1999@gmail.com
License: UNKNOWN
Platform: UNKNOWN
Classifier: Programming Language :: Python :: 3
Classifier: License :: OSI Approved :: MIT License
Classifier: Operating System :: OS Independent
License-File: LICENSE
